mc_game1/__init__.py
mc_game1-1.0.0.dist-info/METADATA
mc_game1-1.0.0.dist-info/WHEEL
mc_game1-1.0.0.dist-info/top_level.txt
mc_game1-1.0.0.dist-info/RECORD
