Metadata-Version: 2.1
Name: mc-game1
Version: 1.0.0
Summary: A mc game.
Home-page: https://www.github.com/
Author: bob
Author-email: 56141537@qq.com
Classifier: Programming Language :: Python :: 3
Classifier: License :: OSI Approved :: MIT License
Classifier: Operating System :: OS Independent
